my_package/__init__.py
my_unique_package_name-0.1.dist-info/METADATA
my_unique_package_name-0.1.dist-info/WHEEL
my_unique_package_name-0.1.dist-info/entry_points.txt
my_unique_package_name-0.1.dist-info/top_level.txt
my_unique_package_name-0.1.dist-info/RECORD
