Metadata-Version: 2.1
Name: my-unique-package-name
Version: 0.1
Summary: A simple package to print COMS W3132 UNI
Home-page: https://github.com/yourusername/my_package
Author: Your Name
Author-email: your_email@example.com
Classifier: Programming Language :: Python :: 3
Classifier: License :: OSI Approved :: MIT License
Classifier: Operating System :: OS Independent
Requires-Python: >=3.6
